ECE410/Assignments/Assignment2/src/BarrelShifterGeneric.vhd
LIBRARY IEEE;
USE IEEE.std_logic_1164.ALL;

ENTITY BarrelShifterGeneric IS
  GENERIC (N : NATURAL RANGE 2 TO 128);
  PORT (
    d_in  : IN STD_LOGIC_VECTOR(N - 1 DOWNTO 0);
    d_out : OUT STD_LOGIC_VECTOR(N - 1 DOWNTO 0);
    rot   : IN INTEGER RANGE 0 TO N - 1);
END;

ARCHITECTURE Behavioural OF BarrelShifterGeneric IS
BEGIN
  d_out <= d_in ROR rot;
END;

Assignments/Assignment2/test/BarrelShifterGeneric_tb.vhd
-- Code your testbench here
LIBRARY IEEE;
USE IEEE.std_logic_1164.ALL;
USE std.env.finish;

ENTITY BarrelShifterGeneric_tb IS

END;

ARCHITECTURE Behavioural OF BarrelShifterGeneric_tb IS
  COMPONENT BarrelShifterGeneric
    GENERIC (N : NATURAL RANGE 2 TO 128);
    PORT (
      d_in  : IN STD_LOGIC_VECTOR(N - 1 DOWNTO 0);
      d_out : OUT STD_LOGIC_VECTOR(N - 1 DOWNTO 0);
      rot   : IN INTEGER RANGE 0 TO N - 1);
  END COMPONENT;
  SIGNAL input   : STD_LOGIC_VECTOR(31 DOWNTO 0) := "01101101011011010110110101101101";
  SIGNAL output  : STD_LOGIC_VECTOR(31 DOWNTO 0) := "00000000000000000000000000000000";
  SIGNAL rot_amt : INTEGER RANGE 0 TO 31         := 0;
BEGIN

  shifter : BarrelShifterGeneric
  GENERIC MAP(N => 32)
  PORT MAP(
    d_in  => input,
    d_out => output,
    rot   => rot_amt);

  PROCESS
  BEGIN

    rot_amt <= 0;
    WAIT FOR 10 ns;
    rot_amt <= 1;
    WAIT FOR 10 ns;
    rot_amt <= 2;
    WAIT FOR 10 ns;
    rot_amt <= 3;
    WAIT FOR 10 ns;
    rot_amt <= 4;
    WAIT FOR 10 ns;
    rot_amt <= 5;
    WAIT FOR 10 ns;
    rot_amt <= 6;
    WAIT FOR 10 ns;
    rot_amt <= 7;
    WAIT FOR 10 ns;

    finish;

  END PROCESS;
END ARCHITECTURE;

ECE410/Assignments/Assignment2/simulation/BarrelShifterGeneric_tb.vcd
$date
  Mon Oct 11 22:09:03 2021
$end
$version
  GHDL v0
$end
$timescale
  1 fs
$end
$scope module standard $end
$upscope $end
$scope module textio $end
$upscope $end
$scope module std_logic_1164 $end
$upscope $end
$scope module env $end
$upscope $end
$scope module barrelshiftergeneric_tb $end
$var reg 32 ! input[31:0] $end
$var reg 32 " output[31:0] $end
$var integer 32 # rot_amt $end
$scope module shifter $end
$var reg 32 $ d_in[31:0] $end
$var reg 32 % d_out[31:0] $end
$var integer 32 & rot $end
$upscope $end
$upscope $end
$enddefinitions $end
#0
b01101101011011010110110101101101 !
b01101101011011010110110101101101 "
b0 #
b01101101011011010110110101101101 $
b01101101011011010110110101101101 %
b0 &
#10000000
b10110110101101101011011010110110 "
b1 #
b10110110101101101011011010110110 %
b1 &
#20000000
b01011011010110110101101101011011 "
b10 #
b01011011010110110101101101011011 %
b10 &
#30000000
b10101101101011011010110110101101 "
b11 #
b10101101101011011010110110101101 %
b11 &
#40000000
b11010110110101101101011011010110 "
b100 #
b11010110110101101101011011010110 %
b100 &
#50000000
b01101011011010110110101101101011 "
b101 #
b01101011011010110110101101101011 %
b101 &
#60000000
b10110101101101011011010110110101 "
b110 #
b10110101101101011011010110110101 %
b110 &
#70000000
b11011010110110101101101011011010 "
b111 #
b11011010110110101101101011011010 %
b111 &
