Labs/Lab2/src/SequenceDetector.vhd
LIBRARY ieee;
USE ieee.std_logic_1164.ALL;

LIBRARY IEEE;
USE IEEE.STD_LOGIC_1164.ALL;

ENTITY SequenceDetector IS
  PORT (
    clk          : IN STD_LOGIC;
    reset        : IN STD_LOGIC;
    seq_in       : IN STD_LOGIC;
    detector_out : OUT STD_LOGIC := '0');
END ENTITY;

ARCHITECTURE Behavioural OF SequenceDetector IS
  TYPE SEQUENCE_STATE IS (A, B, C, D, E);
  SIGNAL state_current : SEQUENCE_STATE;
  SIGNAL state_next    : SEQUENCE_STATE;
BEGIN

  PROCESS (clk, reset)
  BEGIN
    IF reset = '1' THEN
      state_current <= A;
    ELSIF rising_edge(clk) THEN
      state_current <= state_next;
    END IF;
  END PROCESS;

  PROCESS (state_current, seq_in)
  BEGIN
    CASE state_current IS
      WHEN A =>
        IF seq_in = '0' THEN
          state_next   <= A;
          detector_out <= '0';
        ELSE
          state_next   <= B;
          detector_out <= '0';
        END IF;
      WHEN B =>
        IF seq_in = '0' THEN
          state_next   <= A;
          detector_out <= '0';
        ELSE
          state_next   <= C;
          detector_out <= '0';
        END IF;
      WHEN C =>
        IF seq_in = '0' THEN
          state_next   <= D;
          detector_out <= '0';
        ELSE
          state_next   <= C;
          detector_out <= '0';
        END IF;
      WHEN D =>
        IF seq_in = '0' THEN
          state_next   <= A;
          detector_out <= '0';
        ELSE
          state_next   <= E;
          detector_out <= '0';
        END IF;
      WHEN E =>
        IF seq_in = '0' THEN
          state_next   <= A;
          detector_out <= '0';
        ELSE
          state_next   <= C;
          detector_out <= '1';
        END IF;
      WHEN OTHERS =>
        state_next   <= A;
        detector_out <= '0';
    END CASE;
  END PROCESS;
END ARCHITECTURE;

Labs/Lab2/test/SequenceDetector_tb.vhd
LIBRARY ieee;
USE ieee.std_logic_1164.ALL;

USE std.env.finish;

ENTITY SequenceDetector_tb IS
END ENTITY;

ARCHITECTURE Behavioural OF SequenceDetector_tb IS
  COMPONENT SequenceDetector IS PORT (
    clk          : IN STD_LOGIC;
    reset        : IN STD_LOGIC;
    seq_in       : IN STD_LOGIC;
    detector_out : OUT STD_LOGIC);
  END COMPONENT;

  SIGNAL clk_tb          : STD_LOGIC;
  SIGNAL reset_tb        : STD_LOGIC := '1';
  SIGNAL seq_in_tb       : STD_LOGIC := '0';
  SIGNAL detector_out_tb : STD_LOGIC;

  CONSTANT input_stimulus  : STD_LOGIC_VECTOR(0 TO 22) := "01101101110110001101011";
  CONSTANT clock_period_tb : TIME                      := 40 ns; --1/25MHz => 40ns

BEGIN

  detector : SequenceDetector
  PORT MAP(
    clk          => clk_tb,
    reset        => reset_tb,
    seq_in       => seq_in_tb,
    detector_out => detector_out_tb);

  clock :
  PROCESS
  BEGIN
    clk_tb <= '0';
    WAIT FOR clock_period_tb/2;
    clk_tb <= '1';
    WAIT FOR clock_period_tb/2;
  END PROCESS;

  stimulus : PROCESS (clk_tb)
    VARIABLE current_idx : INTEGER := 0;
  BEGIN
    reset_tb <= '0';
    IF rising_edge(clk_tb) THEN
      IF current_idx < input_stimulus'length THEN
        seq_in_tb <= input_stimulus(current_idx);
        current_idx := current_idx + 1;
      ELSE
        finish;
      END IF;
    END IF;

  END PROCESS;
END ARCHITECTURE;

Labs/Lab2/simulation/SequenceDetector_tb.vcd
$date
  Wed Oct 20 14:37:09 2021
$end
$version
  GHDL v0
$end
$timescale
  1 fs
$end
$scope module standard $end
$upscope $end
$scope module textio $end
$upscope $end
$scope module std_logic_1164 $end
$upscope $end
$scope module env $end
$upscope $end
$scope module sequencedetector_tb $end
$var reg 1 ! clk_tb $end
$var reg 1 " reset_tb $end
$var reg 1 # seq_in_tb $end
$var reg 1 $ detector_out_tb $end
$scope module detector $end
$var reg 1 % clk $end
$var reg 1 & reset $end
$var reg 1 ' seq_in $end
$var reg 1 ( detector_out $end
$comment state_current is not handled $end
$comment state_next is not handled $end
$upscope $end
$upscope $end
$enddefinitions $end
#0
0!
0"
0#
0$
0%
0&
0'
0(
#20000000
1!
1%
#40000000
0!
0%
#60000000
1!
1#
1%
1'
#80000000
0!
0%
#100000000
1!
1%
#120000000
0!
0%
#140000000
1!
0#
1%
0'
#160000000
0!
0%
#180000000
1!
1#
1%
1'
#200000000
0!
0%
#220000000
1!
1$
1%
1(
#240000000
0!
0%
#260000000
1!
0#
0$
1%
0'
0(
#280000000
0!
0%
#300000000
1!
1#
1%
1'
#320000000
0!
0%
#340000000
1!
1$
1%
1(
#360000000
0!
0%
#380000000
1!
0$
1%
0(
#400000000
0!
0%
#420000000
1!
0#
1%
0'
#440000000
0!
0%
#460000000
1!
1#
1%
1'
#480000000
0!
0%
#500000000
1!
1$
1%
1(
#520000000
0!
0%
#540000000
1!
0#
0$
1%
0'
0(
#560000000
0!
0%
#580000000
1!
1%
#600000000
0!
0%
#620000000
1!
1%
#640000000
0!
0%
#660000000
1!
1#
1%
1'
#680000000
0!
0%
#700000000
1!
1%
#720000000
0!
0%
#740000000
1!
0#
1%
0'
#760000000
0!
0%
#780000000
1!
1#
1%
1'
#800000000
0!
0%
#820000000
1!
0#
1%
0'
#840000000
0!
0%
#860000000
1!
1#
1%
1'
