Labs/Lab2/src/VendingMachine.vhd

LIBRARY IEEE;
USE IEEE.STD_LOGIC_1164.ALL;
USE ieee.numeric_std.ALL;

ENTITY VendingMachine IS
  PORT (
    clk            : IN STD_LOGIC;
    reset          : IN STD_LOGIC;
    item_sel       : IN STD_LOGIC;                             -- 0 for Soft Drink ($2), 1 for Granola ($4)
    coins_in       : IN STD_LOGIC_VECTOR(1 DOWNTO 0);          -- "00" - 0$, "01" - 1$, "10" - 2$, "11" - 3$
    change_out     : OUT STD_LOGIC_VECTOR(1 DOWNTO 0) := "00"; -- changeout is displayed on two leds - "00" - 0$ "01" - 1$, "10" - 2$ and "11" - 3$
    display_sum    : OUT STD_LOGIC_VECTOR(6 DOWNTO 0);         -- display the current sum of inserted money on the seven segment
    select_segment : OUT STD_LOGIC := '0';                     -- select the left or right segment
    soft_drink     : OUT STD_LOGIC := '0';                     -- turn on the LED to dispense soft drink
    granola_bar    : OUT STD_LOGIC := '0');                    -- turn on the LED to dispense granola bar

END ENTITY;

ARCHITECTURE Behavioral OF VendingMachine IS
  TYPE state_type IS (sum_0, sum_1, sum_2, sum_3, sum_4, sum_5, sum_6, dispense);
  SIGNAL present_state, next_state : state_type;

  VARIABLE selected_item : STD_LOGIC := '0';

  FUNCTION UNSIGNED_TO_SSD(num : POSITIVE RANGE 0 TO 9)
    RETURN STD_LOGIC_VECTOR IS
  BEGIN
    CASE num IS
      WHEN 0 => RETURN "1111110";
      WHEN 1 => RETURN "0110000";
      WHEN 2 => RETURN "1101101";
      WHEN 3 => RETURN "1111001";
      WHEN 4 => RETURN "0110011";
      WHEN 5 => RETURN "1011011";
      WHEN 6 => RETURN "1011111";
      WHEN 7 => RETURN "1110000";
      WHEN 8 => RETURN "1111111";
      WHEN 9 => RETURN "1110011";
    END CASE;
  END FUNCTION;
BEGIN

  PROCESS (clk, reset)
  BEGIN
    IF reset = '1' THEN
      present_state <= sum_0;
    ELSIF rising_edge(clk) THEN
      present_state <= next_state;
    END IF;
  END PROCESS;

  PROCESS (present_state, coins_in)
  BEGIN
    CASE present_state IS
      WHEN sum_0 =>
        soft_drink  <= '0';
        granola_bar <= '0';
        change_out  <= "00";

        display_sum <= UNSIGNED_TO_SSD(0);

        selected_item := item_sel; -- Capture currently selected item into register

        WITH coins_in SELECT
          next_state <= sum_1 WHEN "01",
          next_state <= sum_2 WHEN "10",
          next_state <= sum_3 WHEN "11",
          next_state <= sum_0 WHEN OTHERS;

      WHEN sum_1 =>
        display_sum <= UNSIGNED_TO_SSD(1);

        WITH coins_in SELECT
          next_state <= sum_2 WHEN "01",
          next_state <= sum_3 WHEN "10",
          next_state <= sum_4 WHEN "11",
          next_state <= sum_0 WHEN OTHERS;

      WHEN sum_2 =>
        display_sum <= UNSIGNED_TO_SSD(2);

        IF selected_item = '0' THEN
          next_state <= dispense;
          change_out <= "00";
        ELSE
          WITH coins_in SELECT
            next_state <= sum_3 WHEN "01",
            next_state <= sum_4 WHEN "10",
            next_state <= sum_5 WHEN "11",
            next_state <= sum_0 WHEN OTHERS;
        END IF;

      WHEN sum_3 =>
        display_sum <= UNSIGNED_TO_SSD(3);

        IF selected_item = '0' THEN
          next_state <= dispense;
          change_out <= "01";
        ELSE
          WITH coins_in SELECT
            next_state <= sum_4 WHEN "01",
            next_state <= sum_5 WHEN "10",
            next_state <= sum_6 WHEN "11",
            next_state <= sum_0 WHEN OTHERS;
        END IF;
      WHEN sum_4 =>
        display_sum <= UNSIGNED_TO_SSD(4);

        IF selected_item = '0' THEN
          next_state <= dispense;
          change_out <= "10";
        ELSIF selected_item = '1' THEN
          next_state <= dispense;
          change_out <= "00";
        END IF;

      WHEN sum_5 =>
        display_sum <= UNSIGNED_TO_SSD(5);

        IF selected_item = '0' THEN
          next_state <= dispense;
          change_out <= "11";
        ELSIF selected_item = '1' THEN
          next_state <= dispense;
          change_out <= "01";
        END IF;
      WHEN sum_6 =>
        display_sum <= UNSIGNED_TO_SSD(6);

        IF selected_item = '1' THEN
          next_state <= dispense;
          change_out <= "10";
        END IF;

      WHEN dispense =>
        display_sum <= "0111101";

        IF selected_item = '0' THEN
          soft_drink <= '1';
        ELSE
          granola_bar <= '1';
        END IF;

        next_state <= sum_0;

    END CASE;
  END PROCESS;
END Behavioral;

Labs/Lab2/test/VendingMachine_tb.vhd

LIBRARY IEEE;
USE IEEE.STD_LOGIC_1164.ALL;

USE STD.ENV.finish;

ENTITY VendingMachine_tb IS
END ENTITY;

ARCHITECTURE Behavioral OF VendingMachine_tb IS

  COMPONENT VendingMachine IS
    PORT (
      clk            : IN STD_LOGIC;
      reset          : IN STD_LOGIC;
      item_sel       : IN STD_LOGIC;
      coins_in       : IN STD_LOGIC_VECTOR(1 DOWNTO 0);
      change_out     : OUT STD_LOGIC_VECTOR(1 DOWNTO 0);
      display_sum    : OUT STD_LOGIC_VECTOR(6 DOWNTO 0);
      select_segment : OUT STD_LOGIC;
      soft_drink     : OUT STD_LOGIC;
      granola_bar    : OUT STD_LOGIC);
  END COMPONENT;

  SIGNAL clk_design           : STD_LOGIC                    := '0';
  SIGNAL rst                  : STD_LOGIC                    := '0';
  SIGNAL item_select          : STD_LOGIC                    := '0';
  SIGNAL coins                : STD_LOGIC_VECTOR(1 DOWNTO 0) := "00";
  SIGNAL change               : STD_LOGIC_VECTOR(1 DOWNTO 0) := "00";
  SIGNAL display              : STD_LOGIC_VECTOR(6 DOWNTO 0) := "0000000";
  SIGNAL segment              : STD_LOGIC                    := '0';
  SIGNAL soft_drink_dispense  : STD_LOGIC                    := '0';
  SIGNAL granola_bar_dispense : STD_LOGIC                    := '0';

  CONSTANT clk_period : TIME := 20 ns;

BEGIN
  VENDING_ENT : VendingMachine PORT MAP(
    clk            => clk_design,
    reset          => rst,
    item_sel       => item_select,
    coins_in       => coins,
    change_out     => change,
    display_sum    => display,
    select_segment => segment,
    soft_drink     => soft_drink_dispense,
    granola_bar    => granola_bar_dispense);

  clk_process : PROCESS
  BEGIN
    clk_design <= '1';
    WAIT FOR clk_period/2;
    clk_design <= '0';
    WAIT FOR clk_period/2;
  END PROCESS;

  stim_proc : PROCESS
  BEGIN
    rst <= '1';
    WAIT UNTIL falling_edge(clk_design);

    rst         <= '0';
    item_select <= '0';
    coins       <= "10";
    WAIT UNTIL falling_edge(clk_design);

    coins <= "00";
    WAIT UNTIL falling_edge(clk_design);

    ASSERT soft_drink_dispense = '1'
    REPORT "SOFT DRINK NOT DISPENSED"
      SEVERITY failure;
    WAIT UNTIL falling_edge(clk_design);

    coins <= "01";
    WAIT UNTIL falling_edge(clk_design);

    coins <= "01";
    WAIT UNTIL falling_edge(clk_design);

    coins <= "00";
    WAIT UNTIL falling_edge(clk_design);

    ASSERT soft_drink_dispense = '1'
    REPORT "SOFT DRINK NOT DISPENSED"
      SEVERITY failure;
    WAIT UNTIL falling_edge(clk_design);

    item_select <= '1';
    coins       <= "11";
    WAIT UNTIL falling_edge(clk_design);

    coins <= "11";
    WAIT UNTIL falling_edge(clk_design);

    ASSERT change = "10"
    REPORT "CHANGE NOT DISPENSED"
      SEVERITY failure;
    WAIT UNTIL falling_edge(clk_design);
    WAIT UNTIL falling_edge(clk_design);

    ASSERT granola_bar_dispense = '1'
    REPORT "GRANOLA BAR NOT DISPENSED"
      SEVERITY failure;

    WAIT UNTIL falling_edge(clk_design);

    finish;
  END PROCESS;
END ARCHITECTURE;

Labs/Lab2/simulation/VendingMachine_tb.vcd
$date
  Mon Oct 25 16:45:13 2021
$end
$version
  GHDL v0
$end
$timescale
  1 fs
$end
$scope module standard $end
$upscope $end
$scope module textio $end
$upscope $end
$scope module std_logic_1164 $end
$upscope $end
$scope module env $end
$upscope $end
$scope module numeric_std $end
$upscope $end
$scope module vendingmachine_tb $end
$var reg 1 ! clk_design $end
$var reg 1 " rst $end
$var reg 1 # item_select $end
$var reg 2 $ coins[1:0] $end
$var reg 2 % change[1:0] $end
$var reg 7 & display[6:0] $end
$var reg 1 ' segment $end
$var reg 1 ( soft_drink_dispense $end
$var reg 1 ) granola_bar_dispense $end
$var reg 2 * dispensed[1:0] $end
$scope module vending_ent $end
$var reg 1 + clk $end
$var reg 1 , reset $end
$var reg 1 - item_sel $end
$var reg 2 . coins_in[1:0] $end
$var reg 2 / change_out[1:0] $end
$var reg 7 0 display_sum[6:0] $end
$var reg 1 1 select_segment $end
$var reg 1 2 soft_drink $end
$var reg 1 3 granola_bar $end
$comment present_state is not handled $end
$comment next_state is not handled $end
$upscope $end
$upscope $end
$enddefinitions $end
#0
1!
1"
0#
b00 $
b00 %
b1111110 &
0'
0(
0)
b00 *
1+
1,
0-
b00 .
b00 /
b1111110 0
01
02
03
#10000000
0!
0"
b10 $
0+
0,
b10 .
#20000000
1!
b1101101 &
1+
b1101101 0
#30000000
0!
b00 $
0+
b00 .
#40000000
1!
b0111101 &
1(
1+
b0111101 0
12
#50000000
0!
0+
#60000000
1!
b1111110 &
0(
1+
b1111110 0
02
#70000000
0!
b01 $
0+
b01 .
#80000000
1!
b0110000 &
1+
b0110000 0
#90000000
0!
0+
#100000000
1!
b1101101 &
1+
b1101101 0
#110000000
0!
b00 $
0+
b00 .
#120000000
1!
b0111101 &
1(
1+
b0111101 0
12
#130000000
0!
0+
#140000000
1!
b1111110 &
0(
1+
b1111110 0
02
#150000000
0!
1#
b11 $
0+
1-
b11 .
#160000000
1!
b1111001 &
1+
b1111001 0
#170000000
0!
0+
#180000000
1!
b10 %
b1011111 &
1+
b10 /
b1011111 0
#190000000
0!
0+
#200000000
1!
b00 %
b0110011 &
1+
b00 /
b0110011 0
#210000000
0!
0+
#220000000
1!
b0111101 &
1)
1+
b0111101 0
13
#230000000
0!
0+
#240000000
1!
b1111110 &
0)
1+
b1111110 0
03
