Labs/Lab1/src/full_adder_1bit.vhd
LIBRARY ieee;
USE ieee.std_logic_1164.ALL;
USE ieee.numeric_std.ALL;

ENTITY full_adder_1bit IS
  PORT (
    a     : IN STD_LOGIC;
    b     : IN STD_LOGIC;
    c_in  : IN STD_LOGIC;
    sum   : OUT STD_LOGIC;
    c_out : OUT STD_LOGIC);
END ENTITY;

ARCHITECTURE Dataflow OF full_adder_1bit IS
BEGIN

  sum   <= a XOR b XOR c_in;
  c_out <= (a AND b) OR (b AND c_in) OR (a AND c_in);

END ARCHITECTURE;

Labs/Lab1/src/full_adder_2bit.vhd

LIBRARY ieee;
USE ieee.std_logic_1164.ALL;
USE ieee.numeric_std.ALL;
USE std.env.finish;

ENTITY full_adder_2bit IS
  PORT (
    a     : IN STD_LOGIC_VECTOR(1 DOWNTO 0);
    b     : IN STD_LOGIC_VECTOR(1 DOWNTO 0);
    c_in  : IN STD_LOGIC;
    sum   : OUT STD_LOGIC_VECTOR(1 DOWNTO 0);
    c_out : OUT STD_LOGIC
  );
END ENTITY;

ARCHITECTURE Structural OF full_adder_2bit IS

  -- Component Definitions
  COMPONENT full_adder_1bit IS
    PORT (
      a     : IN STD_LOGIC;
      b     : IN STD_LOGIC;
      c_in  : IN STD_LOGIC;
      sum   : OUT STD_LOGIC;
      c_out : OUT STD_LOGIC
    );
  END COMPONENT;

  -- Signal Definitions
  SIGNAL c_temp : STD_LOGIC := '0';

BEGIN
  --Instantiate components
  adder1 :
  full_adder_1bit PORT MAP(
    a     => a(0),
    b     => b(0),
    c_in  => c_in,
    sum   => sum(0),
    c_out => c_temp
  );

  adder2 :
  full_adder_1bit PORT MAP(
    a     => a(1),
    b     => b(1),
    c_in  => c_temp,
    sum   => sum(1),
    c_out => c_out
  );

END Structural;

Labs/Lab1/test/full_adder_2bit_tb.vhd
LIBRARY ieee;
USE ieee.std_logic_1164.ALL;
USE ieee.numeric_std.ALL;
USE std.env.finish;

ENTITY full_adder_2bit_tb IS
END ENTITY;

ARCHITECTURE Behavioral OF full_adder_2bit_tb IS

  -- Component Definitions
  COMPONENT full_adder_2bit IS
    PORT (
      a     : IN STD_LOGIC_VECTOR(1 DOWNTO 0);
      b     : IN STD_LOGIC_VECTOR(1 DOWNTO 0);
      c_in  : IN STD_LOGIC;
      sum   : OUT STD_LOGIC_VECTOR(1 DOWNTO 0);
      c_out : OUT STD_LOGIC
    );
  END COMPONENT;

  -- Signal Definitions
  SIGNAL a_in_tb    : STD_LOGIC_VECTOR(1 DOWNTO 0) := "00";
  SIGNAL b_in_tb    : STD_LOGIC_VECTOR(1 DOWNTO 0) := "00";
  SIGNAL c_in_tb    : STD_LOGIC                    := '0';
  SIGNAL sum_out_tb : STD_LOGIC_VECTOR(1 DOWNTO 0) := "00";
  SIGNAL c_out_tb   : STD_LOGIC                    := '0';

  --1/25MHz => 40ns
  CONSTANT clock_period_tb : TIME := 40 ns;

BEGIN
  --Instantiate components
  adder :
  full_adder_2bit PORT MAP(
    a     => a_in_tb,
    b     => b_in_tb,
    c_in  => c_in_tb,
    sum   => sum_out_tb,
    c_out => c_out_tb
  );

  PROCESS
    VARIABLE input_vec_tb : STD_LOGIC_VECTOR(4 DOWNTO 0);
  BEGIN
    FOR i IN 0 TO 31 LOOP
      input_vec_tb := STD_LOGIC_VECTOR(TO_UNSIGNED(i, input_vec_tb'length));

      a_in_tb <= input_vec_tb(1 DOWNTO 0);
      b_in_tb <= input_vec_tb(3 DOWNTO 2);
      c_in_tb <= input_vec_tb(4);

      WAIT FOR clock_period_tb;
    END LOOP;

    WAIT FOR clock_period_tb;
    finish;

  END PROCESS;

END Behavioral;

Labs/Lab1/simulation/full_adder_2bit_tb.vcd
$date
  Wed Oct  6 01:02:39 2021
$end
$version
  GHDL v0
$end
$timescale
  1 fs
$end
$scope module standard $end
$upscope $end
$scope module textio $end
$upscope $end
$scope module std_logic_1164 $end
$upscope $end
$scope module numeric_std $end
$upscope $end
$scope module env $end
$upscope $end
$scope module full_adder_2bit_tb $end
$var reg 2 ! a_in_tb[1:0] $end
$var reg 2 " b_in_tb[1:0] $end
$var reg 1 # c_in_tb $end
$var reg 2 $ sum_out_tb[1:0] $end
$var reg 1 % c_out_tb $end
$scope module adder $end
$var reg 2 & a[1:0] $end
$var reg 2 ' b[1:0] $end
$var reg 1 ( c_in $end
$var reg 2 ) sum[1:0] $end
$var reg 1 * c_out $end
$var reg 1 + c_temp $end
$scope module adder1 $end
$var reg 1 , a $end
$var reg 1 - b $end
$var reg 1 . c_in $end
$var reg 1 / sum $end
$var reg 1 0 c_out $end
$upscope $end
$scope module adder2 $end
$var reg 1 1 a $end
$var reg 1 2 b $end
$var reg 1 3 c_in $end
$var reg 1 4 sum $end
$var reg 1 5 c_out $end
$upscope $end
$upscope $end
$upscope $end
$enddefinitions $end
#0
b00 !
b00 "
0#
b00 $
0%
b00 &
b00 '
0(
b00 )
0*
0+
0,
0-
0.
0/
00
01
02
03
04
05
#40000000
b01 !
b01 $
b01 &
b01 )
1,
1/
#80000000
b10 !
b10 $
b10 &
b10 )
0,
0/
11
14
#120000000
b11 !
b11 $
b11 &
b11 )
1,
1/
#160000000
b00 !
b01 "
b01 $
b00 &
b01 '
b01 )
0,
1-
01
04
#200000000
b01 !
b10 $
b01 &
b10 )
1+
1,
0/
10
13
14
#240000000
b10 !
b11 $
0%
b10 &
b11 )
0*
0+
0,
1/
00
11
03
14
05
#280000000
b11 !
b00 $
1%
b11 &
b00 )
1*
1+
1,
0/
10
13
04
15
#320000000
b00 !
b10 "
b10 $
0%
b00 &
b10 '
b10 )
0*
0+
0,
0-
00
01
12
03
14
05
#360000000
b01 !
b11 $
b01 &
b11 )
1,
1/
#400000000
b10 !
b00 $
1%
b10 &
b00 )
1*
0,
0/
11
04
15
#440000000
b11 !
b01 $
b11 &
b01 )
1,
1/
#480000000
b00 !
b11 "
b11 $
0%
b00 &
b11 '
b11 )
0*
0,
1-
01
14
05
#520000000
b01 !
b00 $
1%
b01 &
b00 )
1*
1+
1,
0/
10
13
04
15
#560000000
b10 !
b01 $
b10 &
b01 )
0+
0,
1/
00
11
03
04
#600000000
b11 !
b10 $
b11 &
b10 )
1+
1,
0/
10
13
14
#640000000
b00 !
b00 "
1#
b01 $
0%
b00 &
b00 '
1(
b01 )
0*
0+
0,
0-
1.
1/
00
01
02
03
04
05
#680000000
b01 !
b10 $
b01 &
b10 )
1+
1,
0/
10
13
14
#720000000
b10 !
b11 $
0%
b10 &
b11 )
0*
0+
0,
1/
00
11
03
14
05
#760000000
b11 !
b00 $
1%
b11 &
b00 )
1*
1+
1,
0/
10
13
04
15
#800000000
b00 !
b01 "
b10 $
0%
b00 &
b01 '
b10 )
0*
0,
1-
01
14
05
#840000000
b01 !
b11 $
b01 &
b11 )
1,
1/
#880000000
b10 !
b00 $
1%
b10 &
b00 )
1*
0,
0/
11
04
15
#920000000
b11 !
b01 $
b11 &
b01 )
1,
1/
#960000000
b00 !
b10 "
b11 $
0%
b00 &
b10 '
b11 )
0*
0+
0,
0-
00
01
12
03
14
05
#1000000000
b01 !
b00 $
1%
b01 &
b00 )
1*
1+
1,
0/
10
13
04
15
#1040000000
b10 !
b01 $
b10 &
b01 )
0+
0,
1/
00
11
03
04
#1080000000
b11 !
b10 $
b11 &
b10 )
1+
1,
0/
10
13
14
#1120000000
b00 !
b11 "
b00 $
b00 &
b11 '
b00 )
0,
1-
01
04
#1160000000
b01 !
b01 $
b01 &
b01 )
1,
1/
#1200000000
b10 !
b10 $
b10 &
b10 )
0,
0/
11
14
#1240000000
b11 !
b11 $
b11 &
b11 )
1,
1/
