Labs/Lab1/src/full_adder_1bit.vhd
LIBRARY ieee;
USE ieee.std_logic_1164.ALL;

ENTITY full_adder_1bit IS
  PORT (
    a     : IN STD_LOGIC;
    b     : IN STD_LOGIC;
    c_in  : IN STD_LOGIC;
    sum   : OUT STD_LOGIC;
    c_out : OUT STD_LOGIC);
END ENTITY;

ARCHITECTURE Dataflow OF full_adder_1bit IS
BEGIN

  sum   <= a XOR b XOR c_in;
  c_out <= (a AND b) OR (b AND c_in) OR (a AND c_in);

END ARCHITECTURE;

Labs/Lab1/test/full_adder_1bit_tb.vhd
--------------------------------------------------------------------------------
-- Testbench for 1 bit Full Adder
-- 
-- Authors: Michael Kwok (mkwok1@ualberta.ca)
-- Create Date: 2021-06-10
-- Target: GHDL, Quartus, Vivado
-- 
-- Written in VHDL 2008
--------------------------------------------------------------------------------

LIBRARY ieee;
USE ieee.std_logic_1164.ALL;
USE ieee.numeric_std.ALL;
USE std.env.finish;

ENTITY full_adder_1bit_tb IS
END ENTITY;

ARCHITECTURE Behavioral OF full_adder_1bit_tb IS

  -- Component Definitions
  COMPONENT full_adder_1bit IS
    PORT (
      a     : IN STD_LOGIC;
      b     : IN STD_LOGIC;
      c_in  : IN STD_LOGIC;
      sum   : OUT STD_LOGIC;
      c_out : OUT STD_LOGIC
    );
  END COMPONENT;

  -- Signal Definitions
  SIGNAL a_in_tb    : STD_LOGIC := '0';
  SIGNAL b_in_tb    : STD_LOGIC := '0';
  SIGNAL c_in_tb    : STD_LOGIC := '0';
  SIGNAL sum_out_tb : STD_LOGIC := '0';
  SIGNAL c_out_tb   : STD_LOGIC := '0';

  --1/25MHz => 40ns
  CONSTANT clock_period_tb : TIME := 40 ns;

BEGIN
  --Instantiate components
  adder :
  full_adder_1bit PORT MAP(
    a     => a_in_tb,
    b     => b_in_tb,
    c_in  => c_in_tb,
    sum   => sum_out_tb,
    c_out => c_out_tb
  );

  PROCESS
    VARIABLE input_vec_tb   : UNSIGNED(2 DOWNTO 0);
    VARIABLE expected_sum   : UNSIGNED(1 DOWNTO 0);
    VARIABLE calculated_sum : UNSIGNED(1 DOWNTO 0);
  BEGIN
    FOR i IN 0 TO 7 LOOP
      input_vec_tb := TO_UNSIGNED(i, input_vec_tb'length);
      expected_sum := unsigned'('0' & input_vec_tb(0)) + unsigned'('0' & input_vec_tb(1)) + unsigned'('0' & input_vec_tb(2));

      a_in_tb <= input_vec_tb(0);
      b_in_tb <= input_vec_tb(1);
      c_in_tb <= input_vec_tb(2);

      WAIT FOR clock_period_tb;

      calculated_sum := c_out_tb & sum_out_tb;

      ASSERT calculated_sum = expected_sum
      REPORT "Incorrect Answer. Expected: " & INTEGER'image(TO_INTEGER(expected_sum)) & ". Got: " & INTEGER'image(TO_INTEGER(calculated_sum))
      SEVERITY failure;
    END LOOP;

    WAIT FOR clock_period_tb;
    finish;

  END PROCESS;

END Behavioral;

Labs/Lab1/simulation/full_adder_1bit_tb.vcd
$date
  Wed Oct  6 12:14:49 2021
$end
$version
  GHDL v0
$end
$timescale
  1 fs
$end
$scope module standard $end
$upscope $end
$scope module textio $end
$upscope $end
$scope module std_logic_1164 $end
$upscope $end
$scope module numeric_std $end
$upscope $end
$scope module env $end
$upscope $end
$scope module full_adder_1bit_tb $end
$var reg 1 ! a_in_tb $end
$var reg 1 " b_in_tb $end
$var reg 1 # c_in_tb $end
$var reg 1 $ sum_out_tb $end
$var reg 1 % c_out_tb $end
$scope module adder $end
$var reg 1 & a $end
$var reg 1 ' b $end
$var reg 1 ( c_in $end
$var reg 1 ) sum $end
$var reg 1 * c_out $end
$upscope $end
$upscope $end
$enddefinitions $end
#0
0!
0"
0#
0$
0%
0&
0'
0(
0)
0*
#40000000
1!
1$
1&
1)
#80000000
0!
1"
0&
1'
#120000000
1!
0$
1%
1&
0)
1*
#160000000
0!
0"
1#
1$
0%
0&
0'
1(
1)
0*
#200000000
1!
0$
1%
1&
0)
1*
#240000000
0!
1"
0&
1'
#280000000
1!
1$
1&
1)
