ECE410/Labs/Lab0/src/bcd_counter.vhd
LIBRARY ieee;
USE ieee.std_logic_1164.ALL;
USE ieee.numeric_std.ALL;

ENTITY bcd_counter IS
  PORT (
    clk   : IN STD_LOGIC;
    dir   : IN STD_LOGIC;
    reset : IN STD_LOGIC;
    led   : OUT STD_LOGIC_VECTOR(3 DOWNTO 0)
  );
END ENTITY;

ARCHITECTURE behavioral OF bcd_counter IS
BEGIN

  PROCESS (clk, reset)
  BEGIN
    IF reset = '1' THEN
      led <= "0000";
    ELSIF rising_edge(clk) THEN
      IF dir = '1' THEN
        IF led = "1001" THEN
          led <= "0000";
        ELSE
          led <= STD_LOGIC_VECTOR(UNSIGNED(led) + 1);
        END IF;
      ELSE
        IF led = "0000" THEN
          led <= "1001";
        ELSE
          led <= STD_LOGIC_VECTOR(UNSIGNED(led) - 1);
        END IF;
      END IF;
    END IF;
  END PROCESS;

END ARCHITECTURE;

Labs/Lab0/test/bcd_counter_tb.vhd
----------------------------------------------------------------------------------
-- Company: 
-- Engineer: Shyama Gandhi
-- 
-- Create Date: 07/29/2020 08:32:34 AM
-- Design Name: 
-- Module Name: bcd_tb - Behavioral
-- Project Name: 
-- Target Devices: 
-- Tool Versions: 
-- Description: 
-- 
-- Dependencies: 
-- 
-- Revision:
-- Revision 0.01 - File Created
-- Additional Comments:
-- 
----------------------------------------------------------------------------------

LIBRARY ieee;
USE ieee.std_logic_1164.ALL;
USE ieee.numeric_std.ALL;
USE std.env.finish;

ENTITY bcd_counter_tb IS

END bcd_counter_tb;

ARCHITECTURE behavioral OF bcd_counter_tb IS
  --Include Components
  COMPONENT bcd_counter
    PORT (
      clk   : IN STD_LOGIC;
      dir   : IN STD_LOGIC;
      reset : IN STD_LOGIC;
      led   : OUT STD_LOGIC_VECTOR(3 DOWNTO 0));
  END COMPONENT;

  COMPONENT clk_divider IS
    PORT (
      clk_in  : IN STD_LOGIC;
      clk_out : OUT STD_LOGIC);
  END COMPONENT;

  --Input Signals
  SIGNAL clk_in_tb : STD_LOGIC                    := '0';
  SIGNAL reset_tb  : STD_LOGIC                    := '0';
  SIGNAL dir_tb    : STD_LOGIC                    := '1';
  SIGNAL load_tb   : STD_LOGIC                    := '0';
  SIGNAL count_in  : STD_LOGIC_VECTOR(3 DOWNTO 0) := (OTHERS => '0');

  --Output Signal
  SIGNAL led_tb     : STD_LOGIC_VECTOR(3 DOWNTO 0);
  SIGNAL clk_out_tb : STD_LOGIC := '0';

  --Clock period definition
  CONSTANT clock_period_tb : TIME := 40 ns; --1/25MHz => 40ns

BEGIN
  --Instantiate components
  counter :
  bcd_counter PORT MAP(
    clk   => clk_in_tb,
    dir   => dir_tb,
    reset => reset_tb,
    led   => led_tb
  );

  ----Clock process
  clock :
  PROCESS
  BEGIN
    clk_in_tb <= '0';
    WAIT FOR clock_period_tb/2;
    clk_in_tb <= '1';
    WAIT FOR clock_period_tb/2;
  END PROCESS;

  ----Stimulus process                
  PROCESS
  BEGIN
    reset_tb <= '1'; -- Reset the device under test and setup input to starting state
    WAIT FOR 40 ns;  -- Wait one clock period for our device to reset
    reset_tb <= '0';
    dir_tb   <= '1'; -- this for up counting in the BCD Counter
    -- Clock = 40ns * 2 = 80ns and the total number of counts = 10 so 10 * 80ns = 800ns atleast to see the whole range from 0 to 10.

    WAIT FOR 1000 ns;

    dir_tb <= '0';
    WAIT FOR 500 ns;

    --Asserts are followed by REPORT statement that prints a string report and then followed by severity clauses. ASSERT statements will check for a condition and upon failure of the condition
    --it will report a state.
    --Severity clause will tell you how serious the failed condition is.

    ASSERT(led_tb = "0011")
    REPORT "not zero"
      SEVERITY NOTE;
    finish;

  END PROCESS;

END Behavioral;

Labs/Lab0/simulation/bcd_counter_tb.vcd
$date
  Wed Sep 29 17:27:24 2021
$end
$version
  GHDL v0
$end
$timescale
  1 fs
$end
$scope module standard $end
$upscope $end
$scope module textio $end
$upscope $end
$scope module std_logic_1164 $end
$upscope $end
$scope module numeric_std $end
$upscope $end
$scope module env $end
$upscope $end
$scope module bcd_counter_tb $end
$var reg 1 ! clk_in_tb $end
$var reg 1 " reset_tb $end
$var reg 1 # dir_tb $end
$var reg 1 $ load_tb $end
$var reg 4 % count_in[3:0] $end
$var reg 4 & led_tb[3:0] $end
$var reg 1 ' clk_out_tb $end
$scope module counter $end
$var reg 1 ( clk $end
$var reg 1 ) dir $end
$var reg 1 * reset $end
$var reg 4 + led[3:0] $end
$upscope $end
$upscope $end
$enddefinitions $end
#0
0!
1"
1#
0$
b0000 %
b0000 &
0'
0(
1)
1*
b0000 +
#20000000
1!
1(
#40000000
0!
0"
0(
0*
#60000000
1!
b0001 &
1(
b0001 +
#80000000
0!
0(
#100000000
1!
b0010 &
1(
b0010 +
#120000000
0!
0(
#140000000
1!
b0011 &
1(
b0011 +
#160000000
0!
0(
#180000000
1!
b0100 &
1(
b0100 +
#200000000
0!
0(
#220000000
1!
b0101 &
1(
b0101 +
#240000000
0!
0(
#260000000
1!
b0110 &
1(
b0110 +
#280000000
0!
0(
#300000000
1!
b0111 &
1(
b0111 +
#320000000
0!
0(
#340000000
1!
b1000 &
1(
b1000 +
#360000000
0!
0(
#380000000
1!
b1001 &
1(
b1001 +
#400000000
0!
0(
#420000000
1!
b0000 &
1(
b0000 +
#440000000
0!
0(
#460000000
1!
b0001 &
1(
b0001 +
#480000000
0!
0(
#500000000
1!
b0010 &
1(
b0010 +
#520000000
0!
0(
#540000000
1!
b0011 &
1(
b0011 +
#560000000
0!
0(
#580000000
1!
b0100 &
1(
b0100 +
#600000000
0!
0(
#620000000
1!
b0101 &
1(
b0101 +
#640000000
0!
0(
#660000000
1!
b0110 &
1(
b0110 +
#680000000
0!
0(
#700000000
1!
b0111 &
1(
b0111 +
#720000000
0!
0(
#740000000
1!
b1000 &
1(
b1000 +
#760000000
0!
0(
#780000000
1!
b1001 &
1(
b1001 +
#800000000
0!
0(
#820000000
1!
b0000 &
1(
b0000 +
#840000000
0!
0(
#860000000
1!
b0001 &
1(
b0001 +
#880000000
0!
0(
#900000000
1!
b0010 &
1(
b0010 +
#920000000
0!
0(
#940000000
1!
b0011 &
1(
b0011 +
#960000000
0!
0(
#980000000
1!
b0100 &
1(
b0100 +
#1000000000
0!
0(
#1020000000
1!
b0101 &
1(
b0101 +
#1040000000
0!
0#
0(
0)
#1060000000
1!
b0100 &
1(
b0100 +
#1080000000
0!
0(
#1100000000
1!
b0011 &
1(
b0011 +
#1120000000
0!
0(
#1140000000
1!
b0010 &
1(
b0010 +
#1160000000
0!
0(
#1180000000
1!
b0001 &
1(
b0001 +
#1200000000
0!
0(
#1220000000
1!
b0000 &
1(
b0000 +
#1240000000
0!
0(
#1260000000
1!
b1001 &
1(
b1001 +
#1280000000
0!
0(
#1300000000
1!
b1000 &
1(
b1000 +
#1320000000
0!
0(
#1340000000
1!
b0111 &
1(
b0111 +
#1360000000
0!
0(
#1380000000
1!
b0110 &
1(
b0110 +
#1400000000
0!
0(
#1420000000
1!
b0101 &
1(
b0101 +
#1440000000
0!
0(
#1460000000
1!
b0100 &
1(
b0100 +
#1480000000
0!
0(
#1500000000
1!
b0011 &
1(
b0011 +
